mliv/__init__.py
mliv/dataset/__init__.py
mliv/dataset/demand/__init__.py
mliv/dataset/demand/demand_v1.py
mliv/inference/__init__.py
mliv/inference/deep/__init__.py
mliv/inference/deep/deepiv_v1.py
mliv/inference/deep/dfiv_v1.py
mliv/inference/dflearning/__init__.py
mliv/inference/dflearning/dfl_v1.py
mliv/inference/gmm/__init__.py
mliv/inference/gmm/agmm_v1/__init__.py
mliv/inference/gmm/agmm_v1/net.py
mliv/inference/gmm/agmm_v1/oadam.py
mliv/inference/gmm/agmm_v1/rbflayer.py
mliv/inference/gmm/agmm_v1/trainer.py
mliv/inference/gmm/deepgmm_v1/__init__.py
mliv/inference/gmm/deepgmm_v1/dataclass.py
mliv/inference/gmm/deepgmm_v1/model.py
mliv/inference/gmm/deepgmm_v1/trainer.py
mliv/inference/gmm/deepgmm_v1/nn_structure/__init__.py
mliv/inference/gmm/deepgmm_v1/nn_structure/nn_structure_for_demand_image.py
mliv/inference/gmm/deepgmm_v1/nn_structure/nn_structure_for_demand_old.py
mliv/inference/gmm/deepgmm_v1/nn_structure/nn_structure_for_dsprite.py
mliv/inference/gmm/deepgmm_v1/nn_structure/nn_structure_for_sin.py
mliv/inference/gmm/deepgmm_v1/utils/__init__.py
mliv/inference/gmm/deepgmm_v1/utils/custom_logging.py
mliv/inference/gmm/deepgmm_v1/utils/pytorch_linear_reg_utils.py
mliv/inference/onestage/__init__.py
mliv/inference/onestage/onesiv_v1.py
mliv/inference/sieve/__init__.py
mliv/inference/sieve/dualiv_v1.py
mliv/inference/sieve/kerneliv_v1.py
mliv/inference/twosls/__init__.py
mliv/inference/twosls/nn2sls_v1.py
mliv/inference/twosls/poly2sls_v1.py
mliv/inference/twosls/vanilla2sls_v1.py
mliv/utils/__init__.py
mliv/utils/loaddata.py
mliv/utils/setenv.py
mliv-0.0.2.dist-info/LICENSE
mliv-0.0.2.dist-info/METADATA
mliv-0.0.2.dist-info/WHEEL
mliv-0.0.2.dist-info/top_level.txt
mliv-0.0.2.dist-info/RECORD
