Metadata-Version: 2.1
Name: mliv
Version: 0.0.2
Summary: machine learning for instrumental variable (IV) regression
Home-page: https://github.com/anpwu/mliv.git
Author: anpeng wu
Author-email: anpwu2019@gmail.com
Classifier: Programming Language :: Python
Classifier: License :: OSI Approved :: Apache Software License
Classifier: Operating System :: OS Independent
Requires-Python: >=3.7
License-File: LICENSE
Requires-Dist: argparse
Requires-Dist: pillow
Requires-Dist: numba
Requires-Dist: cvxopt
